[
  {"title":"关山酒","artist":"邓寓君（等什么君）","genre":"国风 · 中文","price":30},
  {"title":"我知道","artist":"BY2","genre":"流行 · 中文","price":30},
  {"title":"弦上生花","artist":"黄霄雲","genre":"流行 · 中文","price":30},
  {"title":"然后呢，最后呢","artist":"黄霄雲","genre":"流行 · 中文","price":30},
  {"title":"别回头（女版）","artist":"辛雯","genre":"流行 · 中文","price":30},
  {"title":"像风一样 (Live)","artist":"单依纯","genre":"流行 · 中文","price":30},
  {"title":"路过人间","artist":"郁可唯","genre":"流行 · 中文","price":30},
  {"title":"慢冷","artist":"梁静茹","genre":"流行 · 中文","price":30},
  {"title":"生生世世爱","artist":"吴雨霏","genre":"流行 · 中文","price":30},
  {"title":"七秒钟的记忆","artist":"徐良、孙羽幽","genre":"流行 · 中文","price":30},
  {"title":"连名带姓","artist":"黄霄雲","genre":"流行 · 中文","price":30},
  {"title":"没了我你依然拥有太阳","artist":"黄霄雲","genre":"流行 · 中文","price":30},
  {"title":"咏春","artist":"七朵组合","genre":"国风 · 中文","price":30},
  {"title":"开往早晨的午夜","artist":"张碧晨","genre":"流行 · 中文","price":30},
  {"title":"如果这就是爱情","artist":"张靓颖","genre":"流行 · 中文","price":30},
  {"title":"带我到山顶（Live）","artist":"王睿卓","genre":"流行 · 中文","price":30},
  {"title":"在加纳共和国离婚（破碎版）","artist":"叶炫清","genre":"流行 · 中文","price":30},
  {"title":"从前说","artist":"小阿七","genre":"流行 · 中文","price":30},
  {"title":"小宇","artist":"蓝心羽","genre":"流行 · 中文","price":30},
  {"title":"我们的爱","artist":"F.I.R.飞儿乐团","genre":"流行 · 中文","price":60},
  {"title":"倒带","artist":"蔡依林","genre":"流行 · 中文","price":30},
  {"title":"冬眠","artist":"司南","genre":"流行 · 中文","price":30},
  {"title":"再见","artist":"G.E.M.邓紫棋","genre":"流行 · 中文","price":30},
  {"title":"甜甜的","artist":"周婕纶","genre":"流行 · 中文","price":30},
  {"title":"花海（女声版）","artist":"夏奈","genre":"流行 · 中文","price":30},
  {"title":"羽化","artist":"单依纯","genre":"古风 · 中文","price":30},
  {"title":"美人鱼","artist":"林俊杰","genre":"流行 · 中文","price":30},
  {"title":"探故知","artist":"浅影阿/汐音社","genre":"古风 · 中文","price":30},
  {"title":"风吹过八千里","artist":"苏星婕","genre":"流行 · 中文","price":30},
  {"title":"七里香 (女声版)","artist":"吉拉朵","genre":"流行 · 中文","price":30},
  {"title":"第三人称","artist":"戚薇","genre":"流行 · 中文","price":30},
  {"title":"消散对白（你眼中深情的对白）","artist":"Sasablue","genre":"流行 · 中文","price":30},
  {"title":"半句再见","artist":"孙燕姿","genre":"流行 · 中文","price":30},
  {"title":"雨天","artist":"孙燕姿","genre":"流行 · 中文","price":30},
  {"title":"这条小鱼在乎（I'm a little fish）","artist":"王OK/洪佩瑜","genre":"流行 · 中文","price":30},
  {"title":"陪你看星星","artist":"陈子晴","genre":"流行 · 中文","price":30},
  {"title":"房间","artist":"刘瑞琦","genre":"流行 · 中文","price":30},
  {"title":"萱草花","artist":"赖美云","genre":"流行 · 中文","price":30},
  {"title":"要不然我们就这样一万年","artist":"黄霄雲","genre":"古风 · 中文","price":60},
  {"title":"Letting Go","artist":"蔡健雅","genre":"流行 · 中文","price":30},
  {"title":"青花","artist":"洋澜一","genre":"流行 · 中文","price":30},
  {"title":"天下","artist":"邓寓君(等什么君)","genre":"古风 · 中文","price":30},
  {"title":"猜不透","artist":"丁当","genre":"流行 · 中文","price":30},
  {"title":"乌兰巴托的夜","artist":"洋澜一","genre":"流行 · 中文","price":30},
  {"title":"传奇","artist":"王菲","genre":"流行 · 中文","price":30},
  {"title":"画（Live Piano Session Ⅱ）","artist":"邓紫棋","genre":"流行 · 中文","price":30},
  {"title":"越来越不懂","artist":"蔡健雅","genre":"流行 · 中文","price":30},
  {"title":"红色高跟鞋","artist":"蔡健雅","genre":"流行 · 中文","price":30},
  {"title":"倒数","artist":"邓紫棋","genre":"流行 · 中文","price":30},
  {"title":"多远都要在一起","artist":"邓紫棋","genre":"流行 · 中文","price":30},
  {"title":"九张机","artist":"锦零","genre":"古风 · 中文","price":30},
  {"title":"至少还有你","artist":"林忆莲","genre":"流行 · 中文","price":30},
  {"title":"美丽的神话","artist":"叶里","genre":"古风 · 中文","price":60},
  {"title":"讲真的","artist":"曾惜","genre":"流行 · 中文","price":30},
  {"title":"落了白","artist":"蒋雪儿Snow.J","genre":"古风 · 中文","price":30},
  {"title":"红尘客栈（女生版）","artist":"Naive.","genre":"古风 · 中文","price":30},
  {"title":"叹云兮","artist":"鞠婧祎","genre":"古风 · 中文","price":30},
  {"title":"爱的回归线","artist":"陈韵若/陈每文","genre":"流行 · 中文","price":30},
  {"title":"下完这场雨（女版）","artist":"琪大妈","genre":"古风 · 中文","price":30},
  {"title":"公主请开心","artist":"小张不嚣张","genre":"流行 · 中文","price":30},
  {"title":"岸边客","artist":"王玉玺","genre":"古风 · 中文","price":30},
  {"title":"九万字","artist":"黄诗扶","genre":"古风 · 中文","price":30},
  {"title":"倾城爱人","artist":"双笙(陈元汐)","genre":"古风 · 中文","price":30},
  {"title":"谪仙","artist":"伊格赛听/叶里","genre":"古风 · 中文","price":30},
  {"title":"爱殇","artist":"小时姑娘","genre":"流行 · 中文","price":60},
  {"title":"牵丝戏","artist":"银临，Aki阿杰","genre":"古风 · 中文","price":30},
  {"title":"故梦","artist":"双笙","genre":"古风 · 中文","price":30},
  {"title":"怜悯（Live）","artist":"周深","genre":"古风 · 中文","price":60},
  {"title":"当爱","artist":"黄霄雲","genre":"古风 · 中文","price":30},
  {"title":"如果当时（女声版）","artist":"叶子舒","genre":"古风 · 中文","price":30},
  {"title":"云裳羽衣曲","artist":"周深","genre":"古风 · 中文","price":30},
  {"title":"如故","artist":"张碧晨","genre":"古风 · 中文","price":30},
  {"title":"千古","artist":"阿兰","genre":"古风 · 中文","price":30},
  {"title":"西楼别序","artist":"尹昔眠/小田音乐社","genre":"古风 · 中文","price":30},
  {"title":"若梦","artist":"周深","genre":"古风 · 中文","price":30},
  {"title":"此生不换","artist":"青鸟飞鱼","genre":"古风 · 中文","price":30},
  {"title":"大鱼","artist":"周深","genre":"古风 · 中文","price":60},
  {"title":"云烟成雨","artist":"房东的猫","genre":"民谣 · 中文","price":30},
  {"title":"走马","artist":"陈粒","genre":"民谣 · 中文","price":30},
  {"title":"奇妙能力歌","artist":"陈粒","genre":"民谣 · 中文","price":30},
  {"title":"虚拟","artist":"陈粒","genre":"民谣 · 中文","price":30},
  {"title":"光","artist":"陈粒","genre":"民谣 · 中文","price":30}
]

